codeowners_diff.py
codeowners_diff-0.2.0.dist-info/licenses/LICENSE
codeowners_diff-0.2.0.dist-info/METADATA
codeowners_diff-0.2.0.dist-info/WHEEL
codeowners_diff-0.2.0.dist-info/entry_points.txt
codeowners_diff-0.2.0.dist-info/top_level.txt
codeowners_diff-0.2.0.dist-info/RECORD
