Metadata-Version: 2.4
Name: codeowners_diff
Version: 0.2.0
Summary: see which files have changed ownership when `CODEOWNERS` changes
Author-email: Samuel Searles-Bryant <sam@samueljsb.co.uk>
License-Expression: MIT
Project-URL: Source, https://github.com/samueljsb/codeowners-diff
Project-URL: Changelog, https://github.com/samueljsb/codeowners-diff/blob/main/CHANGELOG.md
Classifier: Programming Language :: Python :: 3 :: Only
Classifier: Programming Language :: Python :: 3
Classifier: Programming Language :: Python :: 3.10
Classifier: Programming Language :: Python :: 3.11
Classifier: Programming Language :: Python :: 3.12
Classifier: Programming Language :: Python :: 3.13
Requires-Python: >=3.10
License-File: LICENSE
Requires-Dist: codeowners
Requires-Dist: tabulate
Dynamic: license-file
